saml2-stubs/METADATA.toml
saml2-stubs/__init__.pyi
saml2-stubs/algsupport.pyi
saml2-stubs/argtree.pyi
saml2-stubs/assertion.pyi
saml2-stubs/attribute_converter.pyi
saml2-stubs/attribute_resolver.pyi
saml2-stubs/authn.pyi
saml2-stubs/cache.pyi
saml2-stubs/cert.pyi
saml2-stubs/client.pyi
saml2-stubs/client_base.pyi
saml2-stubs/config.pyi
saml2-stubs/country_codes.pyi
saml2-stubs/discovery.pyi
saml2-stubs/ecp.pyi
saml2-stubs/ecp_client.pyi
saml2-stubs/entity.pyi
saml2-stubs/eptid.pyi
saml2-stubs/filter.pyi
saml2-stubs/httpbase.pyi
saml2-stubs/httputil.pyi
saml2-stubs/ident.pyi
saml2-stubs/mcache.pyi
saml2-stubs/md.pyi
saml2-stubs/mdbcache.pyi
saml2-stubs/mdie.pyi
saml2-stubs/mdstore.pyi
saml2-stubs/metadata.pyi
saml2-stubs/mongo_store.pyi
saml2-stubs/pack.pyi
saml2-stubs/population.pyi
saml2-stubs/request.pyi
saml2-stubs/response.pyi
saml2-stubs/s_utils.pyi
saml2-stubs/saml.pyi
saml2-stubs/samlp.pyi
saml2-stubs/sdb.pyi
saml2-stubs/server.pyi
saml2-stubs/sigver.pyi
saml2-stubs/soap.pyi
saml2-stubs/time_util.pyi
saml2-stubs/validate.pyi
saml2-stubs/version.pyi
saml2-stubs/virtual_org.pyi
saml2-stubs/attributemaps/__init__.pyi
saml2-stubs/attributemaps/adfs_v1x.pyi
saml2-stubs/attributemaps/adfs_v20.pyi
saml2-stubs/attributemaps/basic.pyi
saml2-stubs/attributemaps/saml_uri.pyi
saml2-stubs/attributemaps/shibboleth_uri.pyi
saml2-stubs/authn_context/__init__.pyi
saml2-stubs/authn_context/ippword.pyi
saml2-stubs/authn_context/mobiletwofactor.pyi
saml2-stubs/authn_context/ppt.pyi
saml2-stubs/authn_context/pword.pyi
saml2-stubs/authn_context/sslcert.pyi
saml2-stubs/authn_context/timesync.pyi
saml2-stubs/cryptography/__init__.pyi
saml2-stubs/cryptography/asymmetric.pyi
saml2-stubs/cryptography/errors.pyi
saml2-stubs/cryptography/pki.pyi
saml2-stubs/cryptography/symmetric.pyi
saml2-stubs/data/__init__.pyi
saml2-stubs/data/schemas/__init__.pyi
saml2-stubs/data/templates/__init__.pyi
saml2-stubs/entity_category/__init__.pyi
saml2-stubs/entity_category/at_egov_pvp2.pyi
types_pysaml2-1.0.1.dist-info/LICENSE
types_pysaml2-1.0.1.dist-info/METADATA
types_pysaml2-1.0.1.dist-info/WHEEL
types_pysaml2-1.0.1.dist-info/top_level.txt
types_pysaml2-1.0.1.dist-info/RECORD
