Metadata-Version: 2.1
Name: types-pysaml2
Version: 1.0.1
Summary: Type Stubs for pysaml2
Home-page: https://github.com/cex-solutions/pysaml2
Author: Binovate Labs
Author-email: cex-dev@binovate.com
License: GPLv3
Project-URL: Bug Reports, https://github.com/cex-solutions/types-pysaml2/issues
Project-URL: Source, https://github.com/cex-solutions/types-pysaml2
Keywords: stubs pysaml2 pysaml saml2 saml
Classifier: Development Status :: 3 - Alpha
Classifier: Intended Audience :: Developers
Classifier: License :: OSI Approved :: GNU General Public License v3 or later (GPLv3+)
Classifier: Typing :: Stubs Only
Classifier: Programming Language :: Python :: 3 :: Only
Classifier: Programming Language :: Python :: 3.7
Classifier: Programming Language :: Python :: 3.8
Classifier: Programming Language :: Python :: 3.9
Classifier: Programming Language :: Python :: 3.10
Requires-Python: >=3.7, <4
License-File: LICENSE
Provides-Extra: dev
Requires-Dist: pysaml2 (==7.2.1) ; extra == 'dev'
Requires-Dist: types-six (==1.16.21.4) ; extra == 'dev'
Requires-Dist: types-requests (==2.28.11.7) ; extra == 'dev'
Requires-Dist: mypy (==0.991) ; extra == 'dev'
Requires-Dist: pipenv-setup (==3.2.0) ; extra == 'dev'
Requires-Dist: twine (==4.0.2) ; extra == 'dev'
